README.rst
setup.py
pagerdutyapi/__init__.py
pagerdutyapi/contexts.py
pagerdutyapi/exceptions.py
pagerdutyapi/handlers.py
pagerdutyapi.egg-info/PKG-INFO
pagerdutyapi.egg-info/SOURCES.txt
pagerdutyapi.egg-info/dependency_links.txt
pagerdutyapi.egg-info/requires.txt
pagerdutyapi.egg-info/top_level.txt